{"cameraMode":{"drawMode":0,"name":"Shaded","section":"Shading Mode"},"sceneLighting":false,"audioPlay":false,"sceneViewState":{"m_AlwaysRefresh":false,"showFog":true,"showSkybox":false,"showFlares":true,"showImageEffects":true,"showParticleSystems":true,"showVisualEffectGraphs":true,"m_FxEnabled":true},"in2DMode":false,"pivot":{"x":563.4000244140625,"y":260.0,"z":0.0},"rotation":{"x":-0.2764873802661896,"y":0.08978082239627838,"z":-0.02595546282827854,"w":-0.9564763307571411},"size":608.810546875,"orthographic":false}